nats_view/__init__.py
nats_view/main.py
nats_view-0.2.1.dist-info/entry_points.txt
nats_view-0.2.1.dist-info/METADATA
nats_view-0.2.1.dist-info/WHEEL
nats_view-0.2.1.dist-info/RECORD
