Metadata-Version: 2.4
Name: nats-view
Version: 0.2.1
Summary: NATS JetStream topic watcher
Author: User
Author-email: user@example.com
Requires-Python: >=3.9
Classifier: Programming Language :: Python :: 3
Classifier: Programming Language :: Python :: 3.9
Classifier: Programming Language :: Python :: 3.10
Classifier: Programming Language :: Python :: 3.11
Classifier: Programming Language :: Python :: 3.12
Classifier: Programming Language :: Python :: 3.13
Classifier: Programming Language :: Python :: 3.14
Requires-Dist: click (>=8.1.0)
Requires-Dist: nats-py (>=2.12.0,<3.0.0)
Requires-Dist: rich (>=14.2.0,<15.0.0)
